{
  "project_info": {
    "project_number": "684536095645",
    "project_id": "mebook-5f10f",
    "storage_bucket": "mebook-5f10f.appspot.com"
  },
  "client": [
    {
      "client_info": {
        "mobilesdk_app_id": "1:684536095645:android:15bc29c1d1bc2d115fc574",
        "android_client_info": {
          "package_name": "www.mebook1"
        }
      },
      "oauth_client": [
        {
          "client_id": "684536095645-tobnhr8aegcteq40vn8tb8o8phojvjr9.apps.googleusercontent.com",
          "client_type": 1,
          "android_info": {
            "package_name": "www.mebook1",
            "certificate_hash": "f8f25021305986e524d2bbbcb8c31a99cd36b40b"
          }
        },
        {
          "client_id": "684536095645-anc8280tih5e7jf128k9osbfe2iclc50.apps.googleusercontent.com",
          "client_type": 3
        }
      ],
      "api_key": [
        {
          "current_key": "AIzaSyDL5lPksBn2tVyTP99lsHe75mouEY6F-uw"
        }
      ],
      "services": {
        "appinvite_service": {
          "other_platform_oauth_client": [
            {
              "client_id": "684536095645-anc8280tih5e7jf128k9osbfe2iclc50.apps.googleusercontent.com",
              "client_type": 3
            }
          ]
        }
      }
    }
  ],
  "configuration_version": "1"
}